gCryptUtil/__init__.py
gCryptUtil/core.py
gCryptUtil-0.2.0.dist-info/LICENSE.txt
gCryptUtil-0.2.0.dist-info/METADATA
gCryptUtil-0.2.0.dist-info/WHEEL
gCryptUtil-0.2.0.dist-info/top_level.txt
gCryptUtil-0.2.0.dist-info/RECORD
