Metadata-Version: 2.1
Name: gCryptUtil
Version: 0.2.0
Summary: extended dictionary class
Home-page: https://github.com/shinaji/gCryptUtil
Author: shinaji
Author-email: shina.synergy@gmail.com
License: MIT
Platform: UNKNOWN
Classifier: Intended Audience :: Developers
Classifier: Development Status :: 4 - Beta
Classifier: Programming Language :: Python :: 3.6
Classifier: Programming Language :: Python :: 3.7
Classifier: Operating System :: OS Independent
Classifier: Topic :: Software Development
Requires-Dist: google-cloud-kms (>=2.0.1)
